odoo/addons/maintenance_account/README.rst
odoo/addons/maintenance_account/__init__.py
odoo/addons/maintenance_account/__manifest__.py
odoo/addons/maintenance_account/i18n/es.po
odoo/addons/maintenance_account/i18n/it.po
odoo/addons/maintenance_account/i18n/maintenance_account.pot
odoo/addons/maintenance_account/models/__init__.py
odoo/addons/maintenance_account/models/account_move.py
odoo/addons/maintenance_account/models/maintenance_equipment.py
odoo/addons/maintenance_account/readme/CONTRIBUTORS.md
odoo/addons/maintenance_account/readme/DESCRIPTION.md
odoo/addons/maintenance_account/readme/USAGE.md
odoo/addons/maintenance_account/static/description/icon.png
odoo/addons/maintenance_account/static/description/index.html
odoo/addons/maintenance_account/tests/__init__.py
odoo/addons/maintenance_account/tests/test_maintenance_account.py
odoo/addons/maintenance_account/views/account_move_view.xml
odoo/addons/maintenance_account/views/maintenance_equipment_view.xml
odoo_addon_maintenance_account-17.0.1.0.0.3.dist-info/METADATA
odoo_addon_maintenance_account-17.0.1.0.0.3.dist-info/WHEEL
odoo_addon_maintenance_account-17.0.1.0.0.3.dist-info/top_level.txt
odoo_addon_maintenance_account-17.0.1.0.0.3.dist-info/RECORD
